{
  "type": "minecraft:crafting_shaped",
  "pattern": [
    "SSS",
    "RH_",
    "SSS"
  ],
  "key": {
    "S": {
      "tag": "securitycraft:reinforced/stone_crafting_materials"
    },
    "H": {
      "item": "securitycraft:reinforced_hopper"
    },
    "_": [
      {
        "item": "securitycraft:reinforced_cobblestone_slab"
      },
      {
        "item": "securitycraft:reinforced_blackstone_slab"
      },
      {
        "item": "securitycraft:reinforced_cobbled_deepslate_slab"
      }
    ],
    "R": {
      "tag": "forge:dusts/redstone"
    }
  },
  "result": {
    "item": "securitycraft:keycard_reader"
  }
}