{
  "type": "minecraft:crafting_shaped",
  "pattern": [
    "DTD",
    "GSG",
    "RER"
  ],
  "key": {
    "D": {
      "type": "forge:ore_dict",
      "ore": "gemDiamond"
    },
    "T": {
      "item": "minecraft:redstone_torch"
    },
    "G": {
      "type": "forge:ore_dict",
      "ore": "ingotGold"
    },
    "S": {
      "type": "forge:ore_dict",
      "ore": "netherStar"
    },
    "R": {
      "type": "forge:ore_dict",
      "ore": "dustRedstone"
    },
    "E": {
      "type": "forge:ore_dict",
      "ore": "gemEmerald"
    }
  },
  "result": {
    "item": "securitycraft:codebreaker",
    "count": 1
  }
}